structured_response/__init__.py
structured_response/response.py
structured_response-0.1.2.dist-info/LICENSE
structured_response-0.1.2.dist-info/METADATA
structured_response-0.1.2.dist-info/WHEEL
structured_response-0.1.2.dist-info/top_level.txt
structured_response-0.1.2.dist-info/RECORD
