Metadata-Version: 2.2
Name: structured_response
Version: 0.1.2
Summary: A simple package to generate structured HTTP responses with trace ID.
Author-email: Rohaan Nadeem <rohaan@rohaannadeem.com>
License: MIT
Project-URL: homepage, https://github.com/rohaan2614/structured-response
Project-URL: repository, https://github.com/rohaan2614/structured-response.git
Project-URL: documentation, https://github.com/rohaan2614/structured-response/wiki
Requires-Python: >=3.8
License-File: LICENSE
Requires-Dist: Flask<4.0,>=3.0.0
